gui/__init__.py
gui/app.py
rcg/__init__.py
rcg/charts.py
rcg/runner.py
rcg/fuzzy/__init__.py
rcg/fuzzy/categories.py
rcg/fuzzy/engine.py
rcg/fuzzy/memberships.py
rcg/fuzzy/rules.py
rcg/fuzzy/test_fuzzy/__init__.py
rcg/fuzzy/test_fuzzy/test_categories.py
rcg/fuzzy/test_fuzzy/test_engine.py
rcg/fuzzy/test_fuzzy/test_memberships.py
rcg/fuzzy/test_fuzzy/test_rules.py
rcg/inp_manage/__init__.py
rcg/inp_manage/inp.py
rcg/inp_manage/test_inp_manage/__init__.py
rcg/inp_manage/test_inp_manage/test_inp.py
rcg-0.1.0.dist-info/LICENSE
rcg-0.1.0.dist-info/METADATA
rcg-0.1.0.dist-info/WHEEL
rcg-0.1.0.dist-info/top_level.txt
rcg-0.1.0.dist-info/RECORD
