Metadata-Version: 2.1
Name: rcg
Version: 0.1.0
Summary: Rapid catchment generator - is a tool for rapid prototyping of a hydraulic model catchments that can be read and edited with SWMM.
Author: Rafał Buczyński
Project-URL: Homepage, https://github.com/BuczynskiRafal/rapid-catchment-generator
License-File: LICENSE
Requires-Dist: scikit-fuzzy
Requires-Dist: numpy
Requires-Dist: pandas
Requires-Dist: swmmio
Requires-Dist: pyswmm
Requires-Dist: matplotlib
